Workbook

Sheet Как пользоваться
A1: I. Финансовая модель «Мегаполис» — ОС v1.0, 26.09.2026
A3: Что это: простая модель денег агентства. Все расчёты — формулы от листа «Вводные».
A4: Синий текст — введённые значения. Чёрный — формулы. Зелёный — ссылки на другой лист.
A5: Жёлтая заливка — допущение или сценарий: ЗАМЕНИТЬ фактом, как только он появится (список — лист «Что заменить»).
A6: Статусы значений: ФАКТ (из брифа или документа) · ОЦЕНКА М (слова Марии) · БЕНЧМАРК (чужой кейс с источником) · ДОПУЩЕНИЕ ОС (цифра для расчёта, не факт).
A8: Листы:
A9: Вводные — все параметры в одном месте, со статусом и источником.
A10: Экономика сделки — сколько остаётся с одной сделки и сколько стоит сделка через платный канал.
A11: Сценарии — год при пессимистичных, базовых и оптимистичных конверсиях. Это СЦЕНАРИИ, не прогноз.
A12: Движение денег — 12 месяцев: остаток, расходы, выплаты комиссий с задержкой. Сценарий выбирается в «Вводных» (ячейка B30).
A13: Каналы — еженедельный учёт расходов и лидов по каналам (заполнять из CRM).
A14: План-факт — сравнение месяца с планом.
... A17: Правило: до 20 реальных лидов конверсии в модели — сценарии. Решения о тратах принимаются по стоп-критериям, а не по модели.

Sheet Вводные
A1: Вводные параметры
A3: Параметр | B3: Значение | C3: Ед. | D3: Статус | E3: Источник / комментарий
A4: Комиссия агентства с одной сделки | B4: 1000000 | C4: ₽ | D4: ОЦЕНКА М | E4: Бриф бизнеса, 24.09.2026. % и сроки по застройщикам неизвестны (J-05)
A5: Налог ИП, доля от дохода | B5: 0.06 | C5: % | D5: ДОПУЩЕНИЕ ОС | E5: Предполагается УСН «доходы» — проверить у бухгалтера (J-10)
A6: Юрист-партнёр на сделку | B6: 30000 | C6: ₽ за сделку | D6: ДОПУЩЕНИЕ ОС | E6: Заменить ценой найденного юриста (J-09)
A7: Вознаграждение за рекомендацию партнёру | B7: 0 | C7: ₽ за сделку | D7: ДОПУЩЕНИЕ ОС | E7: По договорённости с партнёрами (D, шаг 1.2)
A8: Задержка выплаты комиссии после брони | B8: 3 | C8: мес. | D8: ДОПУЩЕНИЕ ОС | E8: Срок бронь → ДДУ → регистрация → выплата. Узнать у TrendAgent и Flat (J-05)
A9: Стартовый капитал (кредит) | B9: 100000 | C9: ₽ | D9: ФАКТ | E9: Бриф бизнеса, 24.09.2026
A10: Лимит платных тестов на 90 дней | B10: 50000 | C10: ₽ | D10: ДОПУЩЕНИЕ ОС | E10: Предложение ОС, решение J-03
A11: Платный бюджет в месяц после 90 дней | B11: 0 | C11: ₽/мес. | D11: ДОПУЩЕНИЕ ОС | E11: 0 до первой выплаты комиссии: иначе кассовый разрыв (см. «Движение денег»). После выплаты — решение М из комиссии (C, Г5)
A13: Постоянные расходы в месяц
A14: AI-подписки (Claude, Perplexity, NotebookLM, Gemini) | B14: 8000 | C14: ₽/мес. | D14: ДОПУЩЕНИЕ ОС | E14: Заменить суммой из выписки
A15: Связь, номер, домен, лендинг | B15: 2000 | C15: ₽/мес. | D15: ДОПУЩЕНИЕ ОС | E15: Заменить фактом
A16: Тариф Авито для недвижимости | B16: 5000 | C16: ₽/мес. | D16: ДОПУЩЕНИЕ ОС | E16: Узнать в кабинете Авито (J-13)
A17: Прочее (поездки на показы и т. п.) | B17: 5000 | C17: ₽/мес. | D17: ДОПУЩЕНИЕ ОС | E17: Заменить фактом
A18: Итого постоянные | B18: =SUM(B14:B17) | C18: ₽/мес. | D18: ФОРМУЛА
A20: Сценарии конверсий
A21: Показатель (сценарий, не факт) | B21: Пессимистичный | C21: Базовый | D21: Оптимистичный | E21: Источник / комментарий | F21: Выбранный
A22: Квалифицированных лидов в месяц из бесплатных каналов (сеть, партнёры, Telegram, Авито-объявления) | B22: 2 | C22: 4 | D22: 8 | E22: ДОПУЩЕНИЕ ОС. Заменить фактом CRM после 2 месяцев | F22: =INDEX(B22:D22,1,$B$30)
A23: Стоимость квалифицированного лида в платном канале | B23: 13300 | C23: 9600 | D23: 6300 | E23: БЕНЧМАРК: кейс ЖК «Режиссер», Краснодар (застройщик, не агентство): 13,3 / 9,6 (среднее) / 6,3 тыс. ₽ [AdIndex, 06.03.2026]. Для Москвы и премиума не проверено | F23: =INDEX(B23:D23,1,$B$30)
A24: Доля квалифицированных, дошедших до диагностики | B24: 0.3 | C24: 0.45 | D24: 0.6 | E24: ДОПУЩЕНИЕ ОС. Заменить фактом CRM после 20 лидов | F24: =INDEX(B24:D24,1,$B$30)
A25: Доля диагностик, дошедших до сделки | B25: 0.05 | C25: 0.1 | D25: 0.15 | E25: ДОПУЩЕНИЕ ОС. Заменить фактом CRM | F25: =INDEX(B25:D25,1,$B$30)
A26: Месяц первой брони (от старта) | B26: 4 | C26: 3 | D26: 2 | E26: ДОПУЩЕНИЕ ОС. Связано с D (этап 3 — дни 61–90) | F26: =INDEX(B26:D26,1,$B$30)
A28: Выбор сценария для листа «Движение денег»
A30: Сценарий (1 — пессимистичный, 2 — базовый, 3 — оптимистичный) | B30: 2

Sheet Экономика сделки
A1: Экономика одной сделки и платного канала
A3: Показатель | B3: Пессимистичный | C3: Базовый | D3: Оптимистичный | E3: Как считается
A4: Комиссия | B4: =Вводные!$B$4 | C4: =Вводные!$B$4 | D4: =Вводные!$B$4 | E4: Вводные B4
A5: Налог | B5: =-B4*Вводные!$B$5 | C5: =-C4*Вводные!$B$5 | D5: =-D4*Вводные!$B$5 | E5: Комиссия × налог
A6: Юрист-партнёр | B6: =-Вводные!$B$6 | C6: =-Вводные!$B$6 | D6: =-Вводные!$B$6 | E6: Вводные B6
A7: Вознаграждение партнёру за рекомендацию | B7: =-Вводные!$B$7 | C7: =-Вводные!$B$7 | D7: =-Вводные!$B$7 | E7: Вводные B7
A8: Остаётся с одной сделки (до маркетинга) | B8: =SUM(B4:B7) | C8: =SUM(C4:C7) | D8: =SUM(D4:D7) | E8: Сумма строк 4–7
A10: Стоимость квалифицированного лида (платный канал) | B10: =Вводные!B23 | C10: =Вводные!C23 | D10: =Вводные!D23 | E10: Сценарий
A11: Квалифицированных лидов на одну сделку | B11: =IFERROR(1/(Вводные!B24*Вводные!B25),0) | C11: =IFERROR(1/(Вводные!C24*Вводные!C25),0) | D11: =IFERROR(1/(Вводные!D24*Вводные!D25),0) | E11: 1 / (доля до диагностики × доля до сделки)
A12: Стоимость привлечения одной сделки через платный канал | B12: =B10*B11 | C12: =C10*C11 | D12: =D10*D11 | E12: Стоимость лида × лидов на сделку
A13: Остаётся с платной сделки | B13: =B8-B12 | C13: =C8-C12 | D13: =D8-D12 | E13: Строка 8 − строка 12
A14: Доля маркетинга в комиссии | B14: =IFERROR(B12/B4,0) | C14: =IFERROR(C12/C4,0) | D14: =IFERROR(D12/D4,0) | E14: Строка 12 / комиссия
A16: Максимальная стоимость квал. лида, при которой маркетинг ≤ 20% комиссии (ориентир для стоп-критерия) | B16: =IFERROR(0.2*B4/B11,0) | C16: =IFERROR(0.2*C4/C11,0) | D16: =IFERROR(0.2*D4/D11,0) | E16: 20% × комиссия / лидов на сделку. Порог 20% — ДОПУЩЕНИЕ ОС, решает М (J-03)

Sheet Сценарии
A1: Год при разных конверсиях (СЦЕНАРИИ, не прогноз)
A3: Показатель за 12 месяцев | B3: Пессимистичный | C3: Базовый | D3: Оптимистичный | E3: Как считается
A4: Платный бюджет за год | B4: =Вводные!$B$10+9*Вводные!$B$11 | C4: =Вводные!$B$10+9*Вводные!$B$11 | D4: =Вводные!$B$10+9*Вводные!$B$11 | E4: Тест 90 дней + 9 мес. × месячный бюджет
A5: Квалифицированных лидов из платного | B5: =IFERROR(B4/Вводные!B23,0) | C5: =IFERROR(C4/Вводные!C23,0) | D5: =IFERROR(D4/Вводные!D23,0) | E5: Бюджет / стоимость квал. лида
A6: Квалифицированных лидов из бесплатных | B6: =Вводные!B22*12 | C6: =Вводные!C22*12 | D6: =Вводные!D22*12 | E6: В месяц × 12
A7: Диагностик | B7: =(B5+B6)*Вводные!B24 | C7: =(C5+C6)*Вводные!C24 | D7: =(D5+D6)*Вводные!D24 | E7: Лиды × доля до диагностики
A8: Сделок (броней) за год | B8: =B7*Вводные!B25 | C8: =C7*Вводные!C25 | D8: =D7*Вводные!D25 | E8: Диагностики × доля до сделки
A9: Сделок с выплатой в пределах года (грубо) | B9: =B8*MAX(0,12-Вводные!$B$8-Вводные!B26+1)/12 | C9: =C8*MAX(0,12-Вводные!$B$8-Вводные!C26+1)/12 | D9: =D8*MAX(0,12-Вводные!$B$8-Вводные!D26+1)/12 | E9: Сделки × доля месяцев, когда выплата успевает прийти
A10: Выручка (комиссии получены) | B10: =B9*Вводные!$B$4 | C10: =C9*Вводные!$B$4 | D10: =D9*Вводные!$B$4 | E10: Сделки с выплатой × комиссия
A11: Расходы: налог и партнёры | B11: =-B9*(Вводные!$B$4*Вводные!$B$5+Вводные!$B$6+Вводные!$B$7) | C11: =-C9*(Вводные!$B$4*Вводные!$B$5+Вводные!$B$6+Вводные!$B$7) | D11: =-D9*(Вводные!$B$4*Вводные!$B$5+Вводные!$B$6+Вводные!$B$7) | E11: На каждую сделку
A12: Расходы: маркетинг | B12: =-B4 | C12: =-C4 | D12: =-D4 | E12: Строка 4
A13: Расходы: постоянные | B13: =-12*Вводные!$B$18 | C13: =-12*Вводные!$B$18 | D13: =-12*Вводные!$B$18 | E13: 12 × постоянные
A14: Результат за год | B14: =SUM(B10:B13) | C14: =SUM(C10:C13) | D14: =SUM(D10:D13) | E14: Выручка − расходы
A15: Минимум J-12: 4 сделки (безубыточность брифа) — выполнен? | B15: =IF(B8>=4,"да","нет") | C15: =IF(C8>=4,"да","нет") | D15: =IF(D8>=4,"да","нет") | E15: Сравнение с целью C

Sheet Движение денег
A1: Движение денег по месяцам (сценарий из Вводные!B30)
A2: ="Сценарий: "&CHOOSE(Вводные!$B$30,"пессимистичный","базовый","оптимистичный")
A4: Строка | B4: М1 | C4: М2 | D4: М3 | E4: М4 | F4: М5 | G4: М6 | H4: М7 | I4: М8 | J4: М9 | K4: М10 | L4: М11 | M4: М12 | N4: Итого
A5: Номер месяца | B5: 1 | C5: 2 | D5: 3 | E5: 4 | F5: 5 | G5: 6 | H5: 7 | I5: 8 | J5: 9 | K5: 10 | L5: 11 | M5: 12
A6: Остаток на начало | B6: =Вводные!$B$9 | C6: =B14 | D6: =C14 | E6: =D14 | F6: =E14 | G6: =F14 | H6: =G14 | I6: =H14 | J6: =I14 | ... M6: =L14
A7: Платный бюджет | B7: =IF(B5=1,0,IF(B5<=3,Вводные!$B$10/2,Вводные!$B$11)) | C7: =IF(C5=1,0,IF(C5<=3,Вводные!$B$10/2,Вводные!$B$11)) | D7: =IF(D5=1,0,IF(D5<=3,Вводные!$B$10/2,Вводные!$B$11)) | E7: =IF(E5=1,0,IF(E5<=3,Вводные!$B$10/2,Вводные!$B$11)) | F7: =IF(F5=1,0,IF(F5<=3,Вводные!$B$10/2,Вводные!$B$11)) | G7: =IF(G5=1,0,IF(G5<=3,Вводные!$B$10/2,Вводные!$B$11)) | H7: =IF(H5=1,0,IF(H5<=3,Вводные!$B$10/2,Вводные!$B$11)) | I7: =IF(I5=1,0,IF(I5<=3,Вводные!$B$10/2,Вводные!$B$11)) | ... M7: =IF(M5=1,0,IF(M5<=3,Вводные!$B$10/2,Вводные!$B$11)) | N7: =SUM(B7:M7)
A8: Постоянные расходы | B8: =Вводные!$B$18 | C8: =Вводные!$B$18 | D8: =Вводные!$B$18 | E8: =Вводные!$B$18 | F8: =Вводные!$B$18 | G8: =Вводные!$B$18 | H8: =Вводные!$B$18 | I8: =Вводные!$B$18 | ... M8: =Вводные!$B$18 | N8: =SUM(B8:M8)
A9: Квал. лидов (бесплатные + платные) | B9: =Вводные!$F$22+IFERROR(B7/Вводные!$F$23,0) | C9: =Вводные!$F$22+IFERROR(C7/Вводные!$F$23,0) | D9: =Вводные!$F$22+IFERROR(D7/Вводные!$F$23,0) | E9: =Вводные!$F$22+IFERROR(E7/Вводные!$F$23,0) | F9: =Вводные!$F$22+IFERROR(F7/Вводные!$F$23,0) | G9: =Вводные!$F$22+IFERROR(G7/Вводные!$F$23,0) | H9: =Вводные!$F$22+IFERROR(H7/Вводные!$F$23,0) | I9: =Вводные!$F$22+IFERROR(I7/Вводные!$F$23,0) | ... M9: =Вводные!$F$22+IFERROR(M7/Вводные!$F$23,0) | N9: =SUM(B9:M9)
A10: Броней (сделок) в месяц | B10: =IF(B5>=Вводные!$F$26,B9*Вводные!$F$24*Вводные!$F$25,0) | C10: =IF(C5>=Вводные!$F$26,C9*Вводные!$F$24*Вводные!$F$25,0) | D10: =IF(D5>=Вводные!$F$26,D9*Вводные!$F$24*Вводные!$F$25,0) | E10: =IF(E5>=Вводные!$F$26,E9*Вводные!$F$24*Вводные!$F$25,0) | F10: =IF(F5>=Вводные!$F$26,F9*Вводные!$F$24*Вводные!$F$25,0) | G10: =IF(G5>=Вводные!$F$26,G9*Вводные!$F$24*Вводные!$F$25,0) | H10: =IF(H5>=Вводные!$F$26,H9*Вводные!$F$24*Вводные!$F$25,0) | I10: =IF(I5>=Вводные!$F$26,I9*Вводные!$F$24*Вводные!$F$25,0) | ... M10: =IF(M5>=Вводные!$F$26,M9*Вводные!$F$24*Вводные!$F$25,0) | N10: =SUM(B10:M10)
A11: Выплат комиссий (сделок) | B11: =IF(B5-Вводные!$B$8>=1,INDEX($B$10:$M$10,1,B5-Вводные!$B$8),0) | C11: =IF(C5-Вводные!$B$8>=1,INDEX($B$10:$M$10,1,C5-Вводные!$B$8),0) | D11: =IF(D5-Вводные!$B$8>=1,INDEX($B$10:$M$10,1,D5-Вводные!$B$8),0) | E11: =IF(E5-Вводные!$B$8>=1,INDEX($B$10:$M$10,1,E5-Вводные!$B$8),0) | F11: =IF(F5-Вводные!$B$8>=1,INDEX($B$10:$M$10,1,F5-Вводные!$B$8),0) | G11: =IF(G5-Вводные!$B$8>=1,INDEX($B$10:$M$10,1,G5-Вводные!$B$8),0) | H11: =IF(H5-Вводные!$B$8>=1,INDEX($B$10:$M$10,1,H5-Вводные!$B$8),0) | I11: =IF(I5-Вводные!$B$8>=1,INDEX($B$10:$M$10,1,I5-Вводные!$B$8),0) | ... M11: =IF(M5-Вводные!$B$8>=1,INDEX($B$10:$M$10,1,M5-Вводные!$B$8),0) | N11: =SUM(B11:M11)
A12: Поступления: комиссии | B12: =B11*Вводные!$B$4 | C12: =C11*Вводные!$B$4 | D12: =D11*Вводные!$B$4 | E12: =E11*Вводные!$B$4 | F12: =F11*Вводные!$B$4 | G12: =G11*Вводные!$B$4 | H12: =H11*Вводные!$B$4 | I12: =I11*Вводные!$B$4 | ... M12: =M11*Вводные!$B$4 | N12: =SUM(B12:M12)
A13: Налог и партнёры | B13: =B11*(Вводные!$B$4*Вводные!$B$5+Вводные!$B$6+Вводные!$B$7) | C13: =C11*(Вводные!$B$4*Вводные!$B$5+Вводные!$B$6+Вводные!$B$7) | D13: =D11*(Вводные!$B$4*Вводные!$B$5+Вводные!$B$6+Вводные!$B$7) | E13: =E11*(Вводные!$B$4*Вводные!$B$5+Вводные!$B$6+Вводные!$B$7) | F13: =F11*(Вводные!$B$4*Вводные!$B$5+Вводные!$B$6+Вводные!$B$7) | G13: =G11*(Вводные!$B$4*Вводные!$B$5+Вводные!$B$6+Вводные!$B$7) | H13: =H11*(Вводные!$B$4*Вводные!$B$5+Вводные!$B$6+Вводные!$B$7) | I13: =I11*(Вводные!$B$4*Вводные!$B$5+Вводные!$B$6+Вводные!$B$7) | ... M13: =M11*(Вводные!$B$4*Вводные!$B$5+Вводные!$B$6+Вводные!$B$7) | N13: =SUM(B13:M13)
A14: Остаток на конец | B14: =B6-B7-B8+B12-B13 | C14: =C6-C7-C8+C12-C13 | D14: =D6-D7-D8+D12-D13 | E14: =E6-E7-E8+E12-E13 | F14: =F6-F7-F8+F12-F13 | G14: =G6-G7-G8+G12-G13 | H14: =H6-H7-H8+H12-H13 | I14: =I6-I7-I8+I12-I13 | ... M14: =M6-M7-M8+M12-M13
A16: Месяц, когда остаток впервые меньше нуля (0 — не уходит в минус) | B16: =IFERROR(MATCH(TRUE,INDEX(B14:M14<0,0),0),0)
A17: Внимание: выплаты «дробные», потому что это ожидаемое значение по сценарию. В жизни сделка — целое число, первая может прийти позже.

Sheet Каналы
A1: Учёт каналов по неделям (заполнять из CRM на еженедельном обзоре)
A3: Неделя (дата понедельника) | B3: Канал | C3: Расход, ₽ | D3: Лидов | E3: Квалифицированных | F3: Диагностик | G3: Стоимость лида | H3: Стоимость квал. лида | I3: Стоимость диагностики | K3: Итого по всем неделям
A4: 28.09.2026 | B4: пример: авито-объявления | C4: 0 | D4: 0 | E4: 0 | F4: 0 | G4: =IF(D4>0,C4/D4,"") | H4: =IF(E4>0,C4/E4,"") | I4: =IF(F4>0,C4/F4,"") | K4: Расход | L4: =SUM(C4:C103)
G5: =IF(D5>0,C5/D5,"") | H5: =IF(E5>0,C5/E5,"") | I5: =IF(F5>0,C5/F5,"") | K5: Лидов | L5: =SUM(D4:D103)
G6: =IF(D6>0,C6/D6,"") | H6: =IF(E6>0,C6/E6,"") | I6: =IF(F6>0,C6/F6,"") | K6: Квалифицированных | L6: =SUM(E4:E103)
G7: =IF(D7>0,C7/D7,"") | H7: =IF(E7>0,C7/E7,"") | I7: =IF(F7>0,C7/F7,"") | K7: Диагностик | L7: =SUM(F4:F103)
G8: =IF(D8>0,C8/D8,"") | H8: =IF(E8>0,C8/E8,"") | I8: =IF(F8>0,C8/F8,"")
G9: =IF(D9>0,C9/D9,"") | H9: =IF(E9>0,C9/E9,"") | I9: =IF(F9>0,C9/F9,"")
G10: =IF(D10>0,C10/D10,"") | H10: =IF(E10>0,C10/E10,"") | I10: =IF(F10>0,C10/F10,"")
G11: =IF(D11>0,C11/D11,"") | H11: =IF(E11>0,C11/E11,"") | I11: =IF(F11>0,C11/F11,"")
G12: =IF(D12>0,C12/D12,"") | H12: =IF(E12>0,C12/E12,"") | I12: =IF(F12>0,C12/F12,"")
G13: =IF(D13>0,C13/D13,"") | H13: =IF(E13>0,C13/E13,"") | I13: =IF(F13>0,C13/F13,"")
G14: =IF(D14>0,C14/D14,"") | H14: =IF(E14>0,C14/E14,"") | I14: =IF(F14>0,C14/F14,"")
G15: =IF(D15>0,C15/D15,"") | H15: =IF(E15>0,C15/E15,"") | I15: =IF(F15>0,C15/F15,"")
G16: =IF(D16>0,C16/D16,"") | H16: =IF(E16>0,C16/E16,"") | I16: =IF(F16>0,C16/F16,"")
G17: =IF(D17>0,C17/D17,"") | H17: =IF(E17>0,C17/E17,"") | I17: =IF(F17>0,C17/F17,"")
G18: =IF(D18>0,C18/D18,"") | H18: =IF(E18>0,C18/E18,"") | I18: =IF(F18>0,C18/F18,"")
G19: =IF(D19>0,C19/D19,"") | H19: =IF(E19>0,C19/E19,"") | I19: =IF(F19>0,C19/F19,"")
... G103: =IF(D103>0,C103/D103,"") | H103: =IF(E103>0,C103/E103,"") | I103: =IF(F103>0,C103/F103,"")

Sheet План-факт
A1: План-факт по месяцам (план — из «Движение денег», факт — вносит М)
A3: Месяц | B3: План: расходы | C3: Факт: расходы | D3: Отклонение | E3: План: броней | F3: Факт: броней | G3: План: поступления | H3: Факт: поступления | I3: Отклонение
A4: М1 | B4: ='Движение денег'!B7+'Движение денег'!B8 | D4: =IF(C4="","",C4-B4) | E4: ='Движение денег'!B10 | G4: ='Движение денег'!B12 | I4: =IF(H4="","",H4-G4)
A5: М2 | B5: ='Движение денег'!C7+'Движение денег'!C8 | D5: =IF(C5="","",C5-B5) | E5: ='Движение денег'!C10 | G5: ='Движение денег'!C12 | I5: =IF(H5="","",H5-G5)
A6: М3 | B6: ='Движение денег'!D7+'Движение денег'!D8 | D6: =IF(C6="","",C6-B6) | E6: ='Движение денег'!D10 | G6: ='Движение денег'!D12 | I6: =IF(H6="","",H6-G6)
A7: М4 | B7: ='Движение денег'!E7+'Движение денег'!E8 | D7: =IF(C7="","",C7-B7) | E7: ='Движение денег'!E10 | G7: ='Движение денег'!E12 | I7: =IF(H7="","",H7-G7)
A8: М5 | B8: ='Движение денег'!F7+'Движение денег'!F8 | D8: =IF(C8="","",C8-B8) | E8: ='Движение денег'!F10 | G8: ='Движение денег'!F12 | I8: =IF(H8="","",H8-G8)
A9: М6 | B9: ='Движение денег'!G7+'Движение денег'!G8 | D9: =IF(C9="","",C9-B9) | E9: ='Движение денег'!G10 | G9: ='Движение денег'!G12 | I9: =IF(H9="","",H9-G9)
A10: М7 | B10: ='Движение денег'!H7+'Движение денег'!H8 | D10: =IF(C10="","",C10-B10) | E10: ='Движение денег'!H10 | G10: ='Движение денег'!H12 | I10: =IF(H10="","",H10-G10)
A11: М8 | B11: ='Движение денег'!I7+'Движение денег'!I8 | D11: =IF(C11="","",C11-B11) | E11: ='Движение денег'!I10 | G11: ='Движение денег'!I12 | I11: =IF(H11="","",H11-G11)
A12: М9 | B12: ='Движение денег'!J7+'Движение денег'!J8 | D12: =IF(C12="","",C12-B12) | E12: ='Движение денег'!J10 | G12: ='Движение денег'!J12 | I12: =IF(H12="","",H12-G12)
A13: М10 | B13: ='Движение денег'!K7+'Движение денег'!K8 | D13: =IF(C13="","",C13-B13) | E13: ='Движение денег'!K10 | G13: ='Движение денег'!K12 | I13: =IF(H13="","",H13-G13)
A14: М11 | B14: ='Движение денег'!L7+'Движение денег'!L8 | D14: =IF(C14="","",C14-B14) | E14: ='Движение денег'!L10 | G14: ='Движение денег'!L12 | I14: =IF(H14="","",H14-G14)
A15: М12 | B15: ='Движение денег'!M7+'Движение денег'!M8 | D15: =IF(C15="","",C15-B15) | E15: ='Движение денег'!M10 | G15: ='Движение денег'!M12 | I15: =IF(H15="","",H15-G15)

Sheet Что заменить
A1: Цифры, которые нужно заменить фактами
A3: Цифра | B3: Где в модели | C3: Где взять факт | D3: Кто | E3: Когда (D) | F3: Решение J
A4: % и сумма комиссии по застройщикам | B4: Вводные B4 | C4: Кабинет TrendAgent, условия Flat | D4: М | E4: Этап 0 (0.5) | F4: J-05
A5: Срок от брони до выплаты | B5: Вводные B8 | C5: TrendAgent, Flat | D5: М | E5: Этап 0 (0.5) | F5: J-05
A6: Налоговый режим и ставка ИП | B6: Вводные B5 | C6: Бухгалтер, документы ИП | D6: М | E6: До первой комиссии | F6: J-10
A7: Стоимость юриста-партнёра | B7: Вводные B6 | C7: Предложение юриста | D7: М | E7: Этап 1 (1.3) | F7: J-09
A8: Тариф Авито | B8: Вводные B16 | C8: Кабинет Авито | D8: М | E8: Этап 1 (1.6) | F8: J-13
A9: AI-подписки, связь, прочее | B9: Вводные B14, B15, B17 | C9: Банковская выписка | D9: М | E9: Неделя 1 | F9: —
A10: Квал. лиды из бесплатных каналов | B10: Вводные B22:D22 | C10: CRM, лист «Каналы» | D10: М | E10: После 2 месяцев | F10: —
A11: Стоимость квал. лида (платный) | B11: Вводные B23:D23 | C11: Тест Авито Рекламы | D11: Рынок + М | E11: Этап 2 (2.5) | F11: J-03
A12: Конверсии до диагностики и сделки | B12: Вводные B24:D25 | C12: CRM после 20 лидов | D12: М | E12: Этап 3 (3.4) | F12: —
A13: Лимит тестов и порог доли маркетинга | B13: Вводные B10; Экономика B16 | C13: Решение М | D13: М | E13: Этап 0 (0.1) | F13: J-03
